portfolio_analytics/__init__.py
portfolio_analytics/analyzer.py
portfolio_analytics/data_provider.py
portfolio_analytics/optimization.py
portfolio_analytics/performance.py
portfolio_analytics/portfolio.py
portfolio_analytics/risk_models.py
portfolio_analytics/visualization.py
portfolio_analytics/sample_data/Sector_ETFs.csv
portfolio_analytics/sample_data/market_data.db
portfolio_analytics/sample_data/snp_500_companies.xlsx
portfolio_analytics_ai-0.2.5.dist-info/METADATA
portfolio_analytics_ai-0.2.5.dist-info/WHEEL
portfolio_analytics_ai-0.2.5.dist-info/top_level.txt
portfolio_analytics_ai-0.2.5.dist-info/RECORD
