Metadata-Version: 2.4
Name: portfolio-analytics-ai
Version: 0.2.5
Summary: AI-powered portfolio analytics and optimization tools
Author-email: Shamit Verma <oss@shamit.in>
Project-URL: Homepage, https://github.com/shamitv/PortfolioAnalyticsAI
Project-URL: Repository, https://github.com/shamitv/PortfolioAnalyticsAI
Project-URL: Issues, https://github.com/shamitv/PortfolioAnalyticsAI/issues
Classifier: Development Status :: 3 - Alpha
Classifier: Intended Audience :: Financial and Insurance Industry
Classifier: License :: OSI Approved :: MIT License
Classifier: Operating System :: OS Independent
Classifier: Programming Language :: Python :: 3
Classifier: Programming Language :: Python :: 3.8
Classifier: Programming Language :: Python :: 3.9
Classifier: Programming Language :: Python :: 3.10
Classifier: Programming Language :: Python :: 3.11
Classifier: Topic :: Office/Business :: Financial :: Investment
Requires-Python: >=3.8
Requires-Dist: numpy>=1.21.0
Requires-Dist: pandas>=1.3.0
Requires-Dist: matplotlib>=3.4.0
Requires-Dist: seaborn>=0.11.0
Requires-Dist: scikit-learn>=1.0.0
Requires-Dist: yfinance>=0.1.87
Requires-Dist: plotly>=5.0.0
Requires-Dist: jupyter>=1.0.0
Requires-Dist: requests>=2.25.0
Provides-Extra: dev
Requires-Dist: pytest>=6.0; extra == "dev"
Requires-Dist: pytest-cov>=2.0; extra == "dev"
Requires-Dist: black>=21.0; extra == "dev"
Requires-Dist: flake8>=3.9; extra == "dev"
Requires-Dist: mypy>=0.910; extra == "dev"
Requires-Dist: pre-commit>=2.15.0; extra == "dev"
